<?xml version="1.0" encoding="UTF-8"?><record_update>
    <sys_choice action="INSERT_OR_UPDATE" field="group" table="x_727664_kaoqin_attendance_info" version="3">
        <sys_choice_set action="INSERT_OR_UPDATE">
            <element>group</element>
            <name>x_727664_kaoqin_attendance_info</name>
            <sys_class_name>sys_choice_set</sys_class_name>
            <sys_created_by>admin</sys_created_by>
            <sys_created_on>2021-12-16 00:44:49</sys_created_on>
            <sys_id>ccd4b5842f200110ed88d5ccf699b67d</sys_id>
            <sys_mod_count>0</sys_mod_count>
            <sys_name>group</sys_name>
            <sys_package display_value="Attendance System" source="x_727664_kaoqin">017a21912f000110ed88d5ccf699b69e</sys_package>
            <sys_policy/>
            <sys_scope display_value="Attendance System">017a21912f000110ed88d5ccf699b69e</sys_scope>
            <sys_update_name>sys_choice_x_727664_kaoqin_attendance_info_group</sys_update_name>
            <sys_updated_by>admin</sys_updated_by>
            <sys_updated_on>2021-12-16 00:44:49</sys_updated_on>
        </sys_choice_set>
        <sys_choice action="INSERT_OR_UPDATE">
            <dependent_value/>
            <element>group</element>
            <hint/>
            <inactive>false</inactive>
            <label>Operation Automation Group</label>
            <language>en</language>
            <name>x_727664_kaoqin_attendance_info</name>
            <sequence/>
            <synonyms/>
            <sys_created_by>admin</sys_created_by>
            <sys_created_on>2021-12-16 00:44:49</sys_created_on>
            <sys_domain>global</sys_domain>
            <sys_domain_path>/</sys_domain_path>
            <sys_id>e8c4f5842f200110ed88d5ccf699b6ab</sys_id>
            <sys_mod_count>1</sys_mod_count>
            <sys_updated_by>admin</sys_updated_by>
            <sys_updated_on>2021-12-16 00:45:01</sys_updated_on>
            <value>Operation Automation Group</value>
        </sys_choice>
        <sys_choice action="INSERT_OR_UPDATE">
            <dependent_value/>
            <element>group</element>
            <hint/>
            <inactive>false</inactive>
            <label>Operation Support Group</label>
            <language>en</language>
            <name>x_727664_kaoqin_attendance_info</name>
            <sequence/>
            <synonyms/>
            <sys_created_by>admin</sys_created_by>
            <sys_created_on>2021-12-16 00:45:20</sys_created_on>
            <sys_domain>global</sys_domain>
            <sys_domain_path>/</sys_domain_path>
            <sys_id>80d479842f200110ed88d5ccf699b662</sys_id>
            <sys_mod_count>1</sys_mod_count>
            <sys_updated_by>admin</sys_updated_by>
            <sys_updated_on>2021-12-16 00:45:25</sys_updated_on>
            <value>Operation Support Group</value>
        </sys_choice>
    </sys_choice>
</record_update>
